bakeapy/__init__.py
bakeapy/__main__.py
bakeapy/cli.py
bake_a_py-1.0.0.dist-info/LICENSE
bake_a_py-1.0.0.dist-info/METADATA
bake_a_py-1.0.0.dist-info/WHEEL
bake_a_py-1.0.0.dist-info/entry_points.txt
bake_a_py-1.0.0.dist-info/top_level.txt
bake_a_py-1.0.0.dist-info/RECORD
