Metadata-Version: 2.1
Name: bake-a-py
Version: 1.0.0
Summary: Variability analysis tool for ROS systems
Home-page: https://github.com/git-afsantos/bake-a-py
Author: André Santos
Author-email: haros.framework@gmail.com
License: MIT
Project-URL: Source, https://github.com/git-afsantos/bake-a-py/
Project-URL: Tracker, https://github.com/git-afsantos/bake-a-py/issues
Keywords: ros,variability,software product lines,feature models
Classifier: Development Status :: 3 - Alpha
Classifier: Intended Audience :: Developers
Classifier: Intended Audience :: Science/Research
Classifier: License :: OSI Approved :: MIT License
Classifier: Operating System :: POSIX :: Linux
Classifier: Programming Language :: Python :: 3
Classifier: Programming Language :: Python :: 3.8
Classifier: Programming Language :: Python :: 3.9
Classifier: Programming Language :: Python :: 3.10
Classifier: Programming Language :: Python :: 3 :: Only
Classifier: Topic :: Scientific/Engineering
Classifier: Topic :: Software Development
Classifier: Topic :: Software Development :: Libraries
Classifier: Topic :: Software Development :: Quality Assurance
Requires-Python: >=3.8, <4
License-File: LICENSE
Provides-Extra: dev
Requires-Dist: pytest ; extra == 'dev'
Requires-Dist: tox ; extra == 'dev'
